{
  "db_name": "PostgreSQL",
  "query": "\n        WITH anchor_items AS (\n            SELECT i.id, i.cluster_id, i.published_at\n            FROM items i\n            INNER JOIN feeds f ON i.source_id = f.source_id\n            LEFT JOIN item_reads ir ON i.id = ir.item_id AND ir.user_id = $1\n            WHERE f.id = $2\n              AND ($3::timestamptz IS NULL OR i.published_at < $3)\n              AND ($4::boolean = false OR (ir.is_read IS NULL OR ir.is_read = false))\n            ORDER BY i.published_at DESC\n            LIMIT $5\n        ),\n        anchor_cluster_ids AS (\n            SELECT DISTINCT cluster_id FROM anchor_items WHERE cluster_id IS NOT NULL\n        )\n        SELECT\n            i.id as \"id!\",\n            array_agg(f.id) as \"feed_ids!\",\n            i.title, i.link, i.content, i.author,\n            i.published_at, i.cluster_id, i.created_at,\n            ir.is_read as \"is_read?\",\n            ROUND(COALESCE(ir.liked, 0.0))::REAL as \"liked?\"\n        FROM items i\n        INNER JOIN sources s ON i.source_id = s.id\n        INNER JOIN feeds f ON f.source_id = s.id\n        LEFT JOIN item_reads ir ON i.id = ir.item_id AND ir.user_id = $1\n        WHERE\n            i.id IN (SELECT id FROM anchor_items)\n            OR\n            (i.cluster_id IS NOT NULL AND i.cluster_id IN (SELECT cluster_id FROM anchor_cluster_ids))\n        GROUP BY i.id, i.title, i.link, i.content, i.author, i.published_at, i.cluster_id, i.created_at, ir.is_read, ir.liked\n        ORDER BY i.published_at DESC\n        ",
  "describe": {
    "columns": [
      {
        "ordinal": 0,
        "name": "id!",
        "type_info": "Uuid"
      },
      {
        "ordinal": 1,
        "name": "feed_ids!",
        "type_info": "UuidArray"
      },
      {
        "ordinal": 2,
        "name": "title",
        "type_info": "Text"
      },
      {
        "ordinal": 3,
        "name": "link",
        "type_info": "Text"
      },
      {
        "ordinal": 4,
        "name": "content",
        "type_info": "Text"
      },
      {
        "ordinal": 5,
        "name": "author",
        "type_info": "Varchar"
      },
      {
        "ordinal": 6,
        "name": "published_at",
        "type_info": "Timestamptz"
      },
      {
        "ordinal": 7,
        "name": "cluster_id",
        "type_info": "Uuid"
      },
      {
        "ordinal": 8,
        "name": "created_at",
        "type_info": "Timestamptz"
      },
      {
        "ordinal": 9,
        "name": "is_read?",
        "type_info": "Bool"
      },
      {
        "ordinal": 10,
        "name": "liked?",
        "type_info": "Float4"
      }
    ],
    "parameters": {
      "Left": [
        "Uuid",
        "Uuid",
        "Timestamptz",
        "Bool",
        "Int8"
      ]
    },
    "nullable": [
      false,
      null,
      false,
      false,
      true,
      true,
      true,
      true,
      true,
      false,
      null
    ]
  },
  "hash": "be3426f24424aded33dc43bc50967cd527dfc8e93e9223b54c31b3def72b7319"
}
